deny/__init__.py
deny/_async/__init__.py
deny/_async/ability.py
deny/_async/policy.py
deny/_sync/__init__.py
deny/_sync/ability.py
deny/_sync/policy.py
deny/action.py
deny/errors.py
deny/ext/__init__.py
deny/ext/errors.py
deny/ext/falcon.py
deny/ext/fastapi.py
deny/ext/flask.py
deny/ext/sanic.py
deny/permission.py
deny/sync.py
deny/utils.py
deny-0.1.1a2.dist-info/LICENSE
deny-0.1.1a2.dist-info/WHEEL
deny-0.1.1a2.dist-info/METADATA
deny-0.1.1a2.dist-info/RECORD
