Metadata-Version: 2.1
Name: deny
Version: 0.1.1a2
Summary: Library for managing permissions in your Python 3.7+ projects
Home-page: https://github.com/holinnn/deny
License: MIT
Author: Aurélien
Author-email: aurelien.amilin@gmail.com
Requires-Python: >=3.7,<4.0
Classifier: License :: OSI Approved :: MIT License
Classifier: Programming Language :: Python :: 3
Classifier: Programming Language :: Python :: 3.10
Classifier: Programming Language :: Python :: 3.7
Classifier: Programming Language :: Python :: 3.8
Classifier: Programming Language :: Python :: 3.9
Project-URL: Repository, https://github.com/holinnn/deny
